pycounts_rory/__init__.py
pycounts_rory/plotting.py
pycounts_rory/pycounts_rory.py
pycounts_rory-1.0.0.dist-info/LICENSE
pycounts_rory-1.0.0.dist-info/METADATA
pycounts_rory-1.0.0.dist-info/WHEEL
pycounts_rory-1.0.0.dist-info/RECORD
